setup.py
fido_probability/Binomialdistribution.py
fido_probability/Gaussiandistribution.py
fido_probability/Generaldistribution.py
fido_probability/__init__.py
fido_probability.egg-info/PKG-INFO
fido_probability.egg-info/SOURCES.txt
fido_probability.egg-info/dependency_links.txt
fido_probability.egg-info/not-zip-safe
fido_probability.egg-info/top_level.txt