Metadata-Version: 1.0
Name: fido-probability
Version: 0.1
Summary: Gaussian and Binomial distributions
Home-page: UNKNOWN
Author: Confidence Vandu
Author-email: confidencevandu@gmail.com
License: UNKNOWN
Platform: UNKNOWN
